[
    {
        "product_name": "Lipton Pure and Light Green Tea Bags, 100 Pieces: Amazon.in: Grocery & Gourmet Foods",
        "total_ratings": "1,277",
        "average_rating": "4.3",
        "groups_by_rating": {
            "5 star": "61%",
            "4 star": "22%",
            "3 star": "8%",
            "2 star": "3%",
            "1 star": "6%"
        },
        "mention_keywords": [
            "times a day",
            "value for money",
            "good taste",
            "taste is good",
            "without sugar",
            "green tea",
            "last 2 years",
            "waste of money",
            "light green",
            "tea bag",
            "within 2 days",
            "earlier orders",
            "drinking green",
            "pure and light"
        ],
        "ratings_by_feature": {
            "Flavor": "4.1",
            "Presentation": "4.3",
            "Scent": "5.0",
            "Value for money": "4.3"
        },
        "reviews": [
            {
                "review_title": "Stapler pins in tea bags",
                "date": "16 May 2019",
                "author_name": "Sameer",
                "author_picture": "https://images-eu.ssl-images-amazon.com/images/S/amazon-avatars-global/default._CR0,0,1024,1024_SX48_.png",
                "rating": "1.0",
                "review_body": "The Better IndiaINDIA, INFORMATIONKnew Stapler Pins in Tea Bags Are Banned? FSSAI Bans You Should Know Aboutby Vidya RajaMay 15, 2019, 4:55 pm1. Stapler pins in tea bagsTea BagsSource: Wikimedia CommonsDo you remember seeing the tea bag stapled in the recent past? If yes, then you can write to the FSSAI and lodge a formal complaint.In July 2017, a circular was issued by the FSSAI banning tea manufacturers from using stapler pins in tea bags.The circular read, “Taking cognisance of the risk to public safety in using staple pins in tea bags by some FBOs, the Food Authority in exercise of the power conferred under Section 16 (5) of FSS Act, 2006, hereby directs the concerned FBOs to discontinue the manufacture, storage, distribution, sale, and import of stapled tea bags by January 1, 2018.”",
                "found_helpful": "29"
            },
            {
                "review_title": "Not green tea",
                "date": "8 June 2017",
                "author_name": "An Amazon Buyer",
                "author_picture": "https://images-eu.ssl-images-amazon.com/images/S/amazon-avatars-global/default._CR0,0,1024,1024_SX48_.png",
                "rating": "1.0",
                "review_body": "I have been drinking green tea for the last 8/9 year. In those years, I have tested products from several brands, including this specific brand. This was my third or fourth purchase of Lipton green tea on Amazon. While I had good experiences with earlier products, this specific order really baffled me. This is ABSOLUTELY not green tea; it doesn't taste like green tea, it doesn't look like green tea. While green tea, when brewed, gives off a pale yellow colour, this one releases a reddish (the colour of normal black tea) colour. If you brew green tea for more than 2/3 minutes, it releases its bitter notes; however, this specific product from Lipton doesn't do that even if you brew for 15 minutes. Another aspect of green tea is that it takes a little time (around 2 minutes) to brew, but put a tea bag of this particular product, the water is instantly red. (See pictures).What is confusing to me is that the earlier orders of this same product were absolutely ok. What happened to this one, did they put normal tea in packets marked as \"Pure & Light Green Tea\"? I don't know. But I am done with Lipton.",
                "found_helpful": "95"
            },
            {
                "review_title": "Not like a green tea",
                "date": "2 December 2018",
                "author_name": "Suneel Kumar",
                "author_picture": "https://images-eu.ssl-images-amazon.com/images/S/amazon-avatars-global/default._CR0,0,1024,1024_SX48_.png",
                "rating": "1.0",
                "review_body": "What is this ? Is this really green tea?I've been drinking Green tea last 2 years. lot of difference in this product. like color, test, packing of green tea etc.When i brewed in water it releases a reddish(as a like black tea ) color, while green tea reflect of a pale yellow color. I had been already ordered green tea from AMAZON. Earlier orders of this same product were good. But what happened on this item? Tested of it not like green tea. What is this?",
                "found_helpful": "23"
            },
            {
                "review_title": "Stay fit or healthy..",
                "date": "3 September 2019",
                "author_name": "Raushan kr",
                "author_picture": "https://images-eu.ssl-images-amazon.com/images/S/amazon-avatars-global/d879ae67-fc1e-46ca-871a-86636d6df0bb._CR0,0,399,399_SX48_.jpg",
                "rating": "5.0",
                "review_body": "Green Tea is the best drink for feeling refreshed that will also help in enhancing your metabolism while promoting weight loss within your body. It is a combination of anti-oxidants and herbal ingredients that help in digestion and cleansing your body. The herbal solution in this tea will deliciously, boost your body’s blood circulation, which will boost the growth of your slimming cells. It also helps in water retention, and also strengthens your immune system. So, say goodbye to common cold, or any other throat problems.",
                "found_helpful": ""
            },
            {
                "review_title": "Subtle and effective",
                "date": "6 April 2019",
                "author_name": "Pune reviewer",
                "author_picture": "https://images-eu.ssl-images-amazon.com/images/S/amazon-avatars-global/default._CR0,0,1024,1024_SX48_.png",
                "rating": "4.0",
                "review_body": "First impression: For the first time it feels odd. But this changes within 2 days of use. It feels good to drink the green tea.If you want strong cup of tea then take less water and vice versa for a lesser strong tea.Overall it is usable. Good to start with. You can continue discovering different tea brands till the time you find that perfect tea.This is also cost effective approximately 3.5 per tea cup.go with smallert pack. You can then order more in case it fits your taste.",
                "found_helpful": "1"
            },
            {
                "review_title": "Taste is good. Green tea is better than normal tea",
                "date": "4 September 2017",
                "author_name": "Deep",
                "author_picture": "https://images-eu.ssl-images-amazon.com/images/S/amazon-avatars-global/5cb914eb-1100-4eed-9fc8-508aea9d79ea._CR23,0,454,454_SX48_.jpg",
                "rating": "5.0",
                "review_body": "Taste is good. Green tea is better than normal tea. It is loaded with lots of health benefits. Shipped in just 2 days. Thanks Amazon for great deal in price and super fast delivery.",
                "found_helpful": "5"
            },
            {
                "review_title": "100 Tea bags at 350/- Worth it.",
                "date": "15 January 2017",
                "author_name": "Riya Banerjee",
                "author_picture": "https://images-eu.ssl-images-amazon.com/images/S/amazon-avatars-global/5089736e-6175-4334-a6ba-dfbc450e5eaa._CR0,0,500,500_SX48_.jpg",
                "rating": "5.0",
                "review_body": "100 Bags are thereVery tasty and the taste is so refreshingI have been drinking green tea to lose weight for the last 6 months. I am a satisfied customer of LIPTON GREEN TEA.",
                "found_helpful": "7"
            },
            {
                "review_title": "Value for money,duh!",
                "date": "30 December 2018",
                "author_name": "Sampriti Mandal",
                "author_picture": "https://images-eu.ssl-images-amazon.com/images/S/amazon-avatars-global/049b0d07-765e-4e31-84c6-1d80f37bf1b2._CR0,0,500,500_SX48_.jpg",
                "rating": "5.0",
                "review_body": "I really got this product at good price..The discount was great even after adding delivery charges,and lipton is always the best! :DThankyou seller💓",
                "found_helpful": "3"
            }
        ]
    }
]